amusing/appconfig.example.yaml
amusing/cli.py
amusing/cli_operations.py
amusing/core/__init__.py
amusing/core/download.py
amusing/core/metadata.py
amusing/core/parse_csv.py
amusing/core/parse_xml.py
amusing/core/save_to_db.py
amusing/core/search.py
amusing/db/__init__.py
amusing/db/engine.py
amusing/db/models.py
amusing/utils/__init__.py
amusing/utils/config.py
amusing/utils/funcs.py
amusing_app-0.4.3.dist-info/METADATA
amusing_app-0.4.3.dist-info/WHEEL
amusing_app-0.4.3.dist-info/entry_points.txt
amusing_app-0.4.3.dist-info/RECORD
