Metadata-Version: 2.3
Name: amusing-app
Version: 0.4.3
Summary: CLI app to download music independently and from your exported Apple Music library.
Author: Yash Prakash
Author-email: yashprakash13@gmail.com
Requires-Python: >=3.10,<4.0
Classifier: Programming Language :: Python :: 3
Classifier: Programming Language :: Python :: 3.10
Classifier: Programming Language :: Python :: 3.11
Classifier: Programming Language :: Python :: 3.12
Classifier: Programming Language :: Python :: 3.13
Requires-Dist: brotli (==1.1.0)
Requires-Dist: certifi (==2023.11.17)
Requires-Dist: charset-normalizer (==3.3.2)
Requires-Dist: click (==8.1.7)
Requires-Dist: idna (==3.6)
Requires-Dist: markdown-it-py (==3.0.0)
Requires-Dist: mdurl (==0.1.2)
Requires-Dist: mutagen (==1.47.0)
Requires-Dist: numpy (==1.26.2)
Requires-Dist: pandas (==2.2.3)
Requires-Dist: pycryptodomex (==3.19.1)
Requires-Dist: pygments (==2.17.2)
Requires-Dist: python-dateutil (==2.8.2)
Requires-Dist: pytz (==2023.3.post1)
Requires-Dist: pyyaml (==6.0.1)
Requires-Dist: requests (==2.31.0)
Requires-Dist: rich (==13.7.0)
Requires-Dist: six (==1.16.0)
Requires-Dist: sqlalchemy
Requires-Dist: typer (==0.9.0)
Requires-Dist: typing-extensions
Requires-Dist: tzdata (==2023.3)
Requires-Dist: unidecode (==1.3.8)
Requires-Dist: urllib3 (==2.1.0)
Requires-Dist: websockets (==12.0)
Requires-Dist: yt-dlp
Requires-Dist: ytmusicapi (==1.3.2)
